yaml2ics.py
yaml2ics-0.3.dist-info/licenses/LICENSE
yaml2ics-0.3.dist-info/METADATA
yaml2ics-0.3.dist-info/WHEEL
yaml2ics-0.3.dist-info/entry_points.txt
yaml2ics-0.3.dist-info/top_level.txt
yaml2ics-0.3.dist-info/RECORD
