Metadata-Version: 2.4
Name: yaml2ics
Version: 0.3
Summary: CLI to convert yaml into ics.
Author: Scientific Python Developers
License: BSD 3-Clause License
Project-URL: Home, https://github.com/scientific-python/yaml2ics
Project-URL: Source, https://github.com/scientific-python/yaml2ics
Classifier: Development Status :: 4 - Beta
Classifier: License :: OSI Approved :: BSD License
Classifier: Programming Language :: Python :: 3
Classifier: Programming Language :: Python :: 3.9
Classifier: Programming Language :: Python :: 3.10
Classifier: Programming Language :: Python :: 3.11
Classifier: Programming Language :: Python :: 3.12
Classifier: Programming Language :: Python :: 3.13
Classifier: Programming Language :: Python :: 3.14
Requires-Python: >=3.9
License-File: LICENSE
Requires-Dist: ics-vtimezones==2020.2
Requires-Dist: ics==0.8.0.dev0
Requires-Dist: python-dateutil>=2.8
Requires-Dist: pyyaml>=6
Requires-Dist: importlib-resources>=5.2.1
Requires-Dist: tzdata; platform_system == "Windows"
Provides-Extra: test
Requires-Dist: pytest>=8.0; extra == "test"
Requires-Dist: pytest-cov>=5.0; extra == "test"
Provides-Extra: lint
Requires-Dist: pre-commit==4.3.0; extra == "lint"
Provides-Extra: dev
Requires-Dist: changelist==0.5; extra == "dev"
Dynamic: license-file
